MANIFEST.in
setup.cfg
setup.py
ringo_tag/__init__.py
ringo_tag/model.py
ringo_tag/tags.json
ringo_tag/tags.xml
ringo_tag/views.py
ringo_tag.egg-info/PKG-INFO
ringo_tag.egg-info/SOURCES.txt
ringo_tag.egg-info/dependency_links.txt
ringo_tag.egg-info/entry_points.txt
ringo_tag.egg-info/not-zip-safe
ringo_tag.egg-info/requires.txt
ringo_tag.egg-info/top_level.txt
ringo_tag/lib/__init__.py
ringo_tag/lib/renderer.py
ringo_tag/locale/ringo_tag.pot