Metadata-Version: 1.0
Name: ringo-tag
Version: 1.0.3
Summary: Tag extention for the ringo webframework
Home-page: UNKNOWN
Author: Torsten Irländer
Author-email: UNKNOWN
License: GPL v2 or later
Keywords: ringo pyramid extension
Platform: UNKNOWN
